openflexure_stage/__init__.py
openflexure_stage/basic_serial_instrument.py
openflexure_stage/stage.py
openflexure_stage-0.2.1.dist-info/DESCRIPTION.rst
openflexure_stage-0.2.1.dist-info/METADATA
openflexure_stage-0.2.1.dist-info/RECORD
openflexure_stage-0.2.1.dist-info/WHEEL
openflexure_stage-0.2.1.dist-info/metadata.json
openflexure_stage-0.2.1.dist-info/top_level.txt
openflexure_stage-0.2.1.dist-info/zip-safe
