Metadata-Version: 2.0
Name: openflexure-stage
Version: 0.2.1
Summary: Control scripts for the OpenFlexure Nano Motor Controller
Home-page: http://www.github.com/rwb27/openflexure_nano_motor_controller
Author: Richard Bowman
Author-email: r.w.bowman@bath.ac.uk
License: UNKNOWN
Download-URL: https://github.com/rwb27/openflexure_nano_motor_controller/archive/v0.1.1.tar.gz
Keywords: arduino,serial,microscope
Platform: UNKNOWN
Classifier: Development Status :: 4 - Beta
Classifier: License :: OSI Approved :: GNU General Public License v3 (GPLv3)
Classifier: Programming Language :: Python :: 2.7
Requires-Dist: future
Requires-Dist: numpy
Requires-Dist: pyserial
